{
  "overall": {
    "mse": {
      "mean": 0.0028993999879519273,
      "std": 0.002435705444574006,
      "median": 0.0029737509321421385
    },
    "ssim": {
      "mean": 0.9550710439838657,
      "std": 0.029071480458472517,
      "median": 0.9564689062841727
    },
    "head_error": {
      "mean": 0.13906678865507777,
      "std": 1.1639844841514486,
      "median": 0.0
    },
    "body_accuracy": {
      "mean": 0.9788045135712109,
      "std": 0.08303896840289161,
      "median": 1.0
    },
    "food_correct": {
      "mean": 0.38243366880146384,
      "std": 0.4859816434480999,
      "median": 0.0
    },
    "head_found": {
      "mean": 0.9862763037511436,
      "std": 0.11634155066065384,
      "median": 1.0
    },
    "food_found": {
      "mean": 0.6450137236962489,
      "std": 0.4785091639036268,
      "median": 1.0
    }
  },
  "per_step": [
    {
      "step": 0,
      "n_episodes": 20,
      "mse_mean": 0.0008154228336422875,
      "mse_std": 0.001244630904407094,
      "ssim_mean": 0.9721298528576682,
      "ssim_std": 0.02079705725044779,
      "head_error_mean": 0.5,
      "head_error_std": 2.179449471770337,
      "body_accuracy_mean": 0.9833333333333332,
      "body_accuracy_std": 0.0726483157256779,
      "food_correct_mean": 0.75,
      "food_correct_std": 0.4330127018922193,
      "head_found_mean": 0.95,
      "head_found_std": 0.21794494717703372,
      "food_found_mean": 0.75,
      "food_found_std": 0.4330127018922193
    },
    {
      "step": 1,
      "n_episodes": 20,
      "mse_mean": 0.0008937360598679333,
      "mse_std": 0.0012973688285833256,
      "ssim_mean": 0.9718689899989279,
      "ssim_std": 0.024787078691603653,
      "head_error_mean": 0.0,
      "head_error_std": 0.0,
      "body_accuracy_mean": 0.9666666666666666,
      "body_accuracy_std": 0.1,
      "food_correct_mean": 0.75,
      "food_correct_std": 0.4330127018922193,
      "head_found_mean": 1.0,
      "head_found_std": 0.0,
      "food_found_mean": 0.75,
      "food_found_std": 0.4330127018922193
    },
    {
      "step": 2,
      "n_episodes": 20,
      "mse_mean": 0.0010705620600560905,
      "mse_std": 0.0014712350505639933,
      "ssim_mean": 0.9715249761304492,
      "ssim_std": 0.02411296160049242,
      "head_error_mean": 0.0,
      "head_error_std": 0.0,
      "body_accuracy_mean": 0.9833333333333332,
      "body_accuracy_std": 0.0726483157256779,
      "food_correct_mean": 0.7,
      "food_correct_std": 0.45825756949558394,
      "head_found_mean": 1.0,
      "head_found_std": 0.0,
      "food_found_mean": 0.75,
      "food_found_std": 0.4330127018922193
    },
    {
      "step": 3,
      "n_episodes": 20,
      "mse_mean": 0.0016528388249469118,
      "mse_std": 0.0018185418123854709,
      "ssim_mean": 0.964123372978773,
      "ssim_std": 0.02493604892225371,
      "head_error_mean": 0.5,
      "head_error_std": 2.179449471770337,
      "body_accuracy_mean": 0.9666666666666666,
      "body_accuracy_std": 0.1,
      "food_correct_mean": 0.5,
      "food_correct_std": 0.5,
      "head_found_mean": 0.95,
      "head_found_std": 0.21794494717703372,
      "food_found_mean": 0.6,
      "food_found_std": 0.48989794855663565
    },
    {
      "step": 4,
      "n_episodes": 20,
      "mse_mean": 0.0018564163728854056,
      "mse_std": 0.0019942407396706004,
      "ssim_mean": 0.9629662685345937,
      "ssim_std": 0.026857168902199993,
      "head_error_mean": 0.0,
      "head_error_std": 0.0,
      "body_accuracy_mean": 0.9666666666666666,
      "body_accuracy_std": 0.1,
      "food_correct_mean": 0.5,
      "food_correct_std": 0.5,
      "head_found_mean": 1.0,
      "head_found_std": 0.0,
      "food_found_mean": 0.65,
      "food_found_std": 0.47696960070847283
    },
    {
      "step": 5,
      "n_episodes": 20,
      "mse_mean": 0.002006035172155407,
      "mse_std": 0.0019922756841837105,
      "ssim_mean": 0.95973116187354,
      "ssim_std": 0.025865422000383904,
      "head_error_mean": 0.0,
      "head_error_std": 0.0,
      "body_accuracy_mean": 0.9833333333333332,
      "body_accuracy_std": 0.0726483157256779,
      "food_correct_mean": 0.5,
      "food_correct_std": 0.5,
      "head_found_mean": 1.0,
      "head_found_std": 0.0,
      "food_found_mean": 0.65,
      "food_found_std": 0.47696960070847283
    },
    {
      "step": 6,
      "n_episodes": 19,
      "mse_mean": 0.002409203167141976,
      "mse_std": 0.002148610489437385,
      "ssim_mean": 0.9556043740985377,
      "ssim_std": 0.028080180793130426,
      "head_error_mean": 0.05263157894736842,
      "head_error_std": 0.22329687826943606,
      "body_accuracy_mean": 0.9385964912280701,
      "body_accuracy_std": 0.14520127506356886,
      "food_correct_mean": 0.47368421052631576,
      "food_correct_std": 0.49930699897395464,
      "head_found_mean": 1.0,
      "head_found_std": 0.0,
      "food_found_mean": 0.631578947368421,
      "food_found_std": 0.48237638894272
    },
    {
      "step": 7,
      "n_episodes": 18,
      "mse_mean": 0.00219006750312979,
      "mse_std": 0.001994454183974936,
      "ssim_mean": 0.954829759724122,
      "ssim_std": 0.02824235290846568,
      "head_error_mean": 0.0,
      "head_error_std": 0.0,
      "body_accuracy_mean": 0.9629629629629629,
      "body_accuracy_std": 0.10475656017578484,
      "food_correct_mean": 0.4444444444444444,
      "food_correct_std": 0.4969039949999533,
      "head_found_mean": 1.0,
      "head_found_std": 0.0,
      "food_found_mean": 0.6111111111111112,
      "food_found_std": 0.4874980215217845
    },
    {
      "step": 8,
      "n_episodes": 18,
      "mse_mean": 0.0023433472393763724,
      "mse_std": 0.0019462937133508736,
      "ssim_mean": 0.9546924975669376,
      "ssim_std": 0.027044555639879186,
      "head_error_mean": 0.0,
      "head_error_std": 0.0,
      "body_accuracy_mean": 1.0,
      "body_accuracy_std": 0.0,
      "food_correct_mean": 0.4444444444444444,
      "food_correct_std": 0.4969039949999533,
      "head_found_mean": 1.0,
      "head_found_std": 0.0,
      "food_found_mean": 0.6111111111111112,
      "food_found_std": 0.4874980215217845
    },
    {
      "step": 9,
      "n_episodes": 18,
      "mse_mean": 0.0023497743193527437,
      "mse_std": 0.0019264347493155088,
      "ssim_mean": 0.9556994695258985,
      "ssim_std": 0.02776880996145407,
      "head_error_mean": 0.0,
      "head_error_std": 0.0,
      "body_accuracy_mean": 1.0,
      "body_accuracy_std": 0.0,
      "food_correct_mean": 0.3888888888888889,
      "food_correct_std": 0.4874980215217846,
      "head_found_mean": 1.0,
      "head_found_std": 0.0,
      "food_found_mean": 0.5555555555555556,
      "food_found_std": 0.4969039949999533
    },
    {
      "step": 10,
      "n_episodes": 18,
      "mse_mean": 0.002277335628175731,
      "mse_std": 0.001933855805761342,
      "ssim_mean": 0.9567812624738805,
      "ssim_std": 0.027515817821000058,
      "head_error_mean": 0.0,
      "head_error_std": 0.0,
      "body_accuracy_mean": 1.0,
      "body_accuracy_std": 0.0,
      "food_correct_mean": 0.4444444444444444,
      "food_correct_std": 0.4969039949999533,
      "head_found_mean": 1.0,
      "head_found_std": 0.0,
      "food_found_mean": 0.6666666666666666,
      "food_found_std": 0.4714045207910317
    },
    {
      "step": 11,
      "n_episodes": 18,
      "mse_mean": 0.0023606567194684024,
      "mse_std": 0.002020779400287334,
      "ssim_mean": 0.9545223001336475,
      "ssim_std": 0.03212312500637535,
      "head_error_mean": 0.0,
      "head_error_std": 0.0,
      "body_accuracy_mean": 1.0,
      "body_accuracy_std": 0.0,
      "food_correct_mean": 0.4444444444444444,
      "food_correct_std": 0.4969039949999533,
      "head_found_mean": 1.0,
      "head_found_std": 0.0,
      "food_found_mean": 0.6111111111111112,
      "food_found_std": 0.48749802152178456
    },
    {
      "step": 12,
      "n_episodes": 18,
      "mse_mean": 0.0023856542374131903,
      "mse_std": 0.0020708468270932185,
      "ssim_mean": 0.955527494301474,
      "ssim_std": 0.03181191520682245,
      "head_error_mean": 0.0,
      "head_error_std": 0.0,
      "body_accuracy_mean": 1.0,
      "body_accuracy_std": 0.0,
      "food_correct_mean": 0.3888888888888889,
      "food_correct_std": 0.4874980215217846,
      "head_found_mean": 1.0,
      "head_found_std": 0.0,
      "food_found_mean": 0.5555555555555556,
      "food_found_std": 0.4969039949999533
    },
    {
      "step": 13,
      "n_episodes": 18,
      "mse_mean": 0.0024295076144274694,
      "mse_std": 0.0021409796047720375,
      "ssim_mean": 0.956993965100436,
      "ssim_std": 0.03220624302790544,
      "head_error_mean": 0.0,
      "head_error_std": 0.0,
      "body_accuracy_mean": 0.9814814814814814,
      "body_accuracy_std": 0.07635380788180854,
      "food_correct_mean": 0.4444444444444444,
      "food_correct_std": 0.4969039949999533,
      "head_found_mean": 1.0,
      "head_found_std": 0.0,
      "food_found_mean": 0.6666666666666666,
      "food_found_std": 0.4714045207910317
    },
    {
      "step": 14,
      "n_episodes": 18,
      "mse_mean": 0.002608421383886,
      "mse_std": 0.0021198595644506225,
      "ssim_mean": 0.9580416113766383,
      "ssim_std": 0.02691353525567065,
      "head_error_mean": 0.5555555555555556,
      "head_error_std": 2.290614236454256,
      "body_accuracy_mean": 0.9814814814814814,
      "body_accuracy_std": 0.07635380788180854,
      "food_correct_mean": 0.3333333333333333,
      "food_correct_std": 0.4714045207910317,
      "head_found_mean": 0.9444444444444444,
      "head_found_std": 0.2290614236454256,
      "food_found_mean": 0.5555555555555556,
      "food_found_std": 0.4969039949999533
    },
    {
      "step": 15,
      "n_episodes": 18,
      "mse_mean": 0.002686562087199541,
      "mse_std": 0.0020408877637267215,
      "ssim_mean": 0.9544551989486302,
      "ssim_std": 0.030746130462623318,
      "head_error_mean": 0.0,
      "head_error_std": 0.0,
      "body_accuracy_mean": 0.9814814814814814,
      "body_accuracy_std": 0.07635380788180854,
      "food_correct_mean": 0.3333333333333333,
      "food_correct_std": 0.4714045207910317,
      "head_found_mean": 1.0,
      "head_found_std": 0.0,
      "food_found_mean": 0.5555555555555556,
      "food_found_std": 0.4969039949999533
    },
    {
      "step": 16,
      "n_episodes": 18,
      "mse_mean": 0.002675867939198421,
      "mse_std": 0.002231415528544662,
      "ssim_mean": 0.9543031059201904,
      "ssim_std": 0.03083637575767061,
      "head_error_mean": 0.0,
      "head_error_std": 0.0,
      "body_accuracy_mean": 0.9814814814814814,
      "body_accuracy_std": 0.07635380788180854,
      "food_correct_mean": 0.3333333333333333,
      "food_correct_std": 0.4714045207910317,
      "head_found_mean": 1.0,
      "head_found_std": 0.0,
      "food_found_mean": 0.6111111111111112,
      "food_found_std": 0.4874980215217845
    },
    {
      "step": 17,
      "n_episodes": 18,
      "mse_mean": 0.0027325634108529406,
      "mse_std": 0.002083479981729164,
      "ssim_mean": 0.9520022363112989,
      "ssim_std": 0.03176987567939054,
      "head_error_mean": 0.0,
      "head_error_std": 0.0,
      "body_accuracy_mean": 0.9814814814814814,
      "body_accuracy_std": 0.07635380788180854,
      "food_correct_mean": 0.3333333333333333,
      "food_correct_std": 0.4714045207910317,
      "head_found_mean": 1.0,
      "head_found_std": 0.0,
      "food_found_mean": 0.5,
      "food_found_std": 0.5
    },
    {
      "step": 18,
      "n_episodes": 18,
      "mse_mean": 0.0028332149908262888,
      "mse_std": 0.00222994663121172,
      "ssim_mean": 0.9502541138966032,
      "ssim_std": 0.0306541398967514,
      "head_error_mean": 0.0,
      "head_error_std": 0.0,
      "body_accuracy_mean": 0.9814814814814814,
      "body_accuracy_std": 0.07635380788180854,
      "food_correct_mean": 0.3333333333333333,
      "food_correct_std": 0.4714045207910317,
      "head_found_mean": 1.0,
      "head_found_std": 0.0,
      "food_found_mean": 0.5555555555555556,
      "food_found_std": 0.4969039949999533
    },
    {
      "step": 19,
      "n_episodes": 18,
      "mse_mean": 0.002705349128063972,
      "mse_std": 0.002177064162490009,
      "ssim_mean": 0.9526821370265787,
      "ssim_std": 0.03278168578083107,
      "head_error_mean": 0.0,
      "head_error_std": 0.0,
      "body_accuracy_mean": 0.9814814814814814,
      "body_accuracy_std": 0.07635380788180854,
      "food_correct_mean": 0.3333333333333333,
      "food_correct_std": 0.4714045207910317,
      "head_found_mean": 1.0,
      "head_found_std": 0.0,
      "food_found_mean": 0.5,
      "food_found_std": 0.5
    },
    {
      "step": 20,
      "n_episodes": 18,
      "mse_mean": 0.0028903597055192323,
      "mse_std": 0.0023345736226364853,
      "ssim_mean": 0.951871827143151,
      "ssim_std": 0.02966634631235154,
      "head_error_mean": 0.0,
      "head_error_std": 0.0,
      "body_accuracy_mean": 0.9814814814814814,
      "body_accuracy_std": 0.07635380788180854,
      "food_correct_mean": 0.3333333333333333,
      "food_correct_std": 0.4714045207910317,
      "head_found_mean": 1.0,
      "head_found_std": 0.0,
      "food_found_mean": 0.5555555555555556,
      "food_found_std": 0.4969039949999533
    },
    {
      "step": 21,
      "n_episodes": 18,
      "mse_mean": 0.002905829841091013,
      "mse_std": 0.0022268020175079213,
      "ssim_mean": 0.9546803718727559,
      "ssim_std": 0.026705951990249978,
      "head_error_mean": 0.5555555555555556,
      "head_error_std": 2.290614236454256,
      "body_accuracy_mean": 0.9814814814814814,
      "body_accuracy_std": 0.07635380788180854,
      "food_correct_mean": 0.3333333333333333,
      "food_correct_std": 0.4714045207910317,
      "head_found_mean": 0.9444444444444444,
      "head_found_std": 0.2290614236454256,
      "food_found_mean": 0.5555555555555556,
      "food_found_std": 0.4969039949999533
    },
    {
      "step": 22,
      "n_episodes": 18,
      "mse_mean": 0.0029140218190504027,
      "mse_std": 0.0022564729874455596,
      "ssim_mean": 0.9514449314008319,
      "ssim_std": 0.029993062928018455,
      "head_error_mean": 0.0,
      "head_error_std": 0.0,
      "body_accuracy_mean": 0.9814814814814814,
      "body_accuracy_std": 0.07635380788180854,
      "food_correct_mean": 0.3333333333333333,
      "food_correct_std": 0.4714045207910317,
      "head_found_mean": 1.0,
      "head_found_std": 0.0,
      "food_found_mean": 0.6111111111111112,
      "food_found_std": 0.4874980215217845
    },
    {
      "step": 23,
      "n_episodes": 18,
      "mse_mean": 0.0028533463017892144,
      "mse_std": 0.0021871780222536092,
      "ssim_mean": 0.9520934062134638,
      "ssim_std": 0.03180101811003788,
      "head_error_mean": 0.0,
      "head_error_std": 0.0,
      "body_accuracy_mean": 0.9814814814814814,
      "body_accuracy_std": 0.07635380788180854,
      "food_correct_mean": 0.3333333333333333,
      "food_correct_std": 0.4714045207910317,
      "head_found_mean": 1.0,
      "head_found_std": 0.0,
      "food_found_mean": 0.5555555555555556,
      "food_found_std": 0.4969039949999533
    },
    {
      "step": 24,
      "n_episodes": 18,
      "mse_mean": 0.002868021334077437,
      "mse_std": 0.0022117474044992765,
      "ssim_mean": 0.9534143241888506,
      "ssim_std": 0.03328678445254556,
      "head_error_mean": 0.0,
      "head_error_std": 0.0,
      "body_accuracy_mean": 0.9814814814814814,
      "body_accuracy_std": 0.07635380788180854,
      "food_correct_mean": 0.3333333333333333,
      "food_correct_std": 0.4714045207910317,
      "head_found_mean": 1.0,
      "head_found_std": 0.0,
      "food_found_mean": 0.5555555555555556,
      "food_found_std": 0.4969039949999533
    },
    {
      "step": 25,
      "n_episodes": 18,
      "mse_mean": 0.0028224184351933624,
      "mse_std": 0.0023472164087426813,
      "ssim_mean": 0.9541416152291118,
      "ssim_std": 0.031883135703754686,
      "head_error_mean": 0.0,
      "head_error_std": 0.0,
      "body_accuracy_mean": 0.9814814814814814,
      "body_accuracy_std": 0.07635380788180854,
      "food_correct_mean": 0.3888888888888889,
      "food_correct_std": 0.4874980215217846,
      "head_found_mean": 1.0,
      "head_found_std": 0.0,
      "food_found_mean": 0.6111111111111112,
      "food_found_std": 0.48749802152178456
    },
    {
      "step": 26,
      "n_episodes": 18,
      "mse_mean": 0.0028699677333053034,
      "mse_std": 0.0023401561434992306,
      "ssim_mean": 0.9520185372435537,
      "ssim_std": 0.029930383875395414,
      "head_error_mean": 0.5555555555555556,
      "head_error_std": 2.290614236454256,
      "body_accuracy_mean": 0.9814814814814814,
      "body_accuracy_std": 0.07635380788180854,
      "food_correct_mean": 0.3888888888888889,
      "food_correct_std": 0.4874980215217846,
      "head_found_mean": 0.9444444444444444,
      "head_found_std": 0.2290614236454256,
      "food_found_mean": 0.6111111111111112,
      "food_found_std": 0.48749802152178456
    },
    {
      "step": 27,
      "n_episodes": 18,
      "mse_mean": 0.002809209892625909,
      "mse_std": 0.0023225712559588776,
      "ssim_mean": 0.9556060190743774,
      "ssim_std": 0.028273147231305622,
      "head_error_mean": 0.0,
      "head_error_std": 0.0,
      "body_accuracy_mean": 0.9814814814814814,
      "body_accuracy_std": 0.07635380788180854,
      "food_correct_mean": 0.3888888888888889,
      "food_correct_std": 0.4874980215217846,
      "head_found_mean": 1.0,
      "head_found_std": 0.0,
      "food_found_mean": 0.6111111111111112,
      "food_found_std": 0.48749802152178456
    },
    {
      "step": 28,
      "n_episodes": 18,
      "mse_mean": 0.0029259823968459386,
      "mse_std": 0.0023922963154620843,
      "ssim_mean": 0.9562120548812866,
      "ssim_std": 0.03076695249619907,
      "head_error_mean": 0.0,
      "head_error_std": 0.0,
      "body_accuracy_mean": 0.9814814814814814,
      "body_accuracy_std": 0.07635380788180854,
      "food_correct_mean": 0.3333333333333333,
      "food_correct_std": 0.4714045207910317,
      "head_found_mean": 1.0,
      "head_found_std": 0.0,
      "food_found_mean": 0.5555555555555556,
      "food_found_std": 0.4969039949999533
    },
    {
      "step": 29,
      "n_episodes": 18,
      "mse_mean": 0.003005266988901035,
      "mse_std": 0.0023802494598745183,
      "ssim_mean": 0.955942565101225,
      "ssim_std": 0.028738531069343466,
      "head_error_mean": 0.0,
      "head_error_std": 0.0,
      "body_accuracy_mean": 0.9814814814814814,
      "body_accuracy_std": 0.07635380788180854,
      "food_correct_mean": 0.3333333333333333,
      "food_correct_std": 0.4714045207910317,
      "head_found_mean": 1.0,
      "head_found_std": 0.0,
      "food_found_mean": 0.6111111111111112,
      "food_found_std": 0.4874980215217845
    },
    {
      "step": 30,
      "n_episodes": 18,
      "mse_mean": 0.003042326154526462,
      "mse_std": 0.0023871776826092732,
      "ssim_mean": 0.9539184671026254,
      "ssim_std": 0.02768717332435187,
      "head_error_mean": 0.0,
      "head_error_std": 0.0,
      "body_accuracy_mean": 0.9814814814814814,
      "body_accuracy_std": 0.07635380788180854,
      "food_correct_mean": 0.3333333333333333,
      "food_correct_std": 0.4714045207910317,
      "head_found_mean": 1.0,
      "head_found_std": 0.0,
      "food_found_mean": 0.6111111111111112,
      "food_found_std": 0.4874980215217845
    },
    {
      "step": 31,
      "n_episodes": 18,
      "mse_mean": 0.002951504849868848,
      "mse_std": 0.002382662969881137,
      "ssim_mean": 0.9538536666512685,
      "ssim_std": 0.029294618100090732,
      "head_error_mean": 0.0,
      "head_error_std": 0.0,
      "body_accuracy_mean": 0.9814814814814814,
      "body_accuracy_std": 0.07635380788180854,
      "food_correct_mean": 0.3888888888888889,
      "food_correct_std": 0.4874980215217846,
      "head_found_mean": 1.0,
      "head_found_std": 0.0,
      "food_found_mean": 0.6666666666666666,
      "food_found_std": 0.4714045207910317
    },
    {
      "step": 32,
      "n_episodes": 18,
      "mse_mean": 0.003148187030212234,
      "mse_std": 0.0024296022338727336,
      "ssim_mean": 0.9557424107619725,
      "ssim_std": 0.026796241821651967,
      "head_error_mean": 0.0,
      "head_error_std": 0.0,
      "body_accuracy_mean": 0.9814814814814814,
      "body_accuracy_std": 0.07635380788180854,
      "food_correct_mean": 0.3333333333333333,
      "food_correct_std": 0.4714045207910317,
      "head_found_mean": 1.0,
      "head_found_std": 0.0,
      "food_found_mean": 0.6111111111111112,
      "food_found_std": 0.4874980215217845
    },
    {
      "step": 33,
      "n_episodes": 18,
      "mse_mean": 0.003169966711564282,
      "mse_std": 0.0025723328725074626,
      "ssim_mean": 0.956588671855109,
      "ssim_std": 0.025513249311998235,
      "head_error_mean": 0.0,
      "head_error_std": 0.0,
      "body_accuracy_mean": 0.9814814814814814,
      "body_accuracy_std": 0.07635380788180854,
      "food_correct_mean": 0.3888888888888889,
      "food_correct_std": 0.4874980215217846,
      "head_found_mean": 1.0,
      "head_found_std": 0.0,
      "food_found_mean": 0.7222222222222222,
      "food_found_std": 0.44790320823880836
    },
    {
      "step": 34,
      "n_episodes": 18,
      "mse_mean": 0.0033296229856760976,
      "mse_std": 0.0024681564413196436,
      "ssim_mean": 0.9543089841889683,
      "ssim_std": 0.02476901546254994,
      "head_error_mean": 0.0,
      "head_error_std": 0.0,
      "body_accuracy_mean": 0.9814814814814814,
      "body_accuracy_std": 0.07635380788180854,
      "food_correct_mean": 0.3333333333333333,
      "food_correct_std": 0.4714045207910317,
      "head_found_mean": 1.0,
      "head_found_std": 0.0,
      "food_found_mean": 0.6666666666666666,
      "food_found_std": 0.4714045207910317
    },
    {
      "step": 35,
      "n_episodes": 18,
      "mse_mean": 0.0032699881959261904,
      "mse_std": 0.0024157142617566695,
      "ssim_mean": 0.9563376930037197,
      "ssim_std": 0.02843575293023035,
      "head_error_mean": 0.0,
      "head_error_std": 0.0,
      "body_accuracy_mean": 0.9814814814814814,
      "body_accuracy_std": 0.07635380788180854,
      "food_correct_mean": 0.3333333333333333,
      "food_correct_std": 0.4714045207910317,
      "head_found_mean": 1.0,
      "head_found_std": 0.0,
      "food_found_mean": 0.6666666666666666,
      "food_found_std": 0.4714045207910317
    },
    {
      "step": 36,
      "n_episodes": 18,
      "mse_mean": 0.003272573950198421,
      "mse_std": 0.002421426182365824,
      "ssim_mean": 0.9522271397192544,
      "ssim_std": 0.030943293878233608,
      "head_error_mean": 0.0,
      "head_error_std": 0.0,
      "body_accuracy_mean": 0.9814814814814814,
      "body_accuracy_std": 0.07635380788180854,
      "food_correct_mean": 0.3333333333333333,
      "food_correct_std": 0.4714045207910317,
      "head_found_mean": 1.0,
      "head_found_std": 0.0,
      "food_found_mean": 0.6111111111111112,
      "food_found_std": 0.48749802152178456
    },
    {
      "step": 37,
      "n_episodes": 18,
      "mse_mean": 0.0032632384158230504,
      "mse_std": 0.002425276635163429,
      "ssim_mean": 0.9525578719965713,
      "ssim_std": 0.030181193407650613,
      "head_error_mean": 0.0,
      "head_error_std": 0.0,
      "body_accuracy_mean": 0.9814814814814814,
      "body_accuracy_std": 0.07635380788180854,
      "food_correct_mean": 0.3333333333333333,
      "food_correct_std": 0.4714045207910317,
      "head_found_mean": 1.0,
      "head_found_std": 0.0,
      "food_found_mean": 0.6666666666666666,
      "food_found_std": 0.4714045207910317
    },
    {
      "step": 38,
      "n_episodes": 18,
      "mse_mean": 0.003427517315483581,
      "mse_std": 0.0025789759324962034,
      "ssim_mean": 0.9527242194147116,
      "ssim_std": 0.02829185214158009,
      "head_error_mean": 1.1111111111111112,
      "head_error_std": 3.1426968052735447,
      "body_accuracy_mean": 0.9629629629629629,
      "body_accuracy_std": 0.10475656017578484,
      "food_correct_mean": 0.3333333333333333,
      "food_correct_std": 0.4714045207910317,
      "head_found_mean": 0.8888888888888888,
      "head_found_std": 0.3142696805273545,
      "food_found_mean": 0.6666666666666666,
      "food_found_std": 0.4714045207910317
    },
    {
      "step": 39,
      "n_episodes": 18,
      "mse_mean": 0.0033503931829462394,
      "mse_std": 0.0025123239355295747,
      "ssim_mean": 0.9531080618372629,
      "ssim_std": 0.0293442509719448,
      "head_error_mean": 0.5555555555555556,
      "head_error_std": 2.290614236454256,
      "body_accuracy_mean": 0.9814814814814814,
      "body_accuracy_std": 0.07635380788180854,
      "food_correct_mean": 0.3333333333333333,
      "food_correct_std": 0.4714045207910317,
      "head_found_mean": 0.9444444444444444,
      "head_found_std": 0.2290614236454256,
      "food_found_mean": 0.6666666666666666,
      "food_found_std": 0.4714045207910317
    },
    {
      "step": 40,
      "n_episodes": 18,
      "mse_mean": 0.0034570339757667374,
      "mse_std": 0.002614199569767009,
      "ssim_mean": 0.954733774650443,
      "ssim_std": 0.026568993719545173,
      "head_error_mean": 0.05555555555555555,
      "head_error_std": 0.2290614236454256,
      "body_accuracy_mean": 0.9814814814814814,
      "body_accuracy_std": 0.07635380788180854,
      "food_correct_mean": 0.3333333333333333,
      "food_correct_std": 0.4714045207910317,
      "head_found_mean": 1.0,
      "head_found_std": 0.0,
      "food_found_mean": 0.6666666666666666,
      "food_found_std": 0.4714045207910317
    },
    {
      "step": 41,
      "n_episodes": 18,
      "mse_mean": 0.003493015555307011,
      "mse_std": 0.002698037920184671,
      "ssim_mean": 0.9546923504185708,
      "ssim_std": 0.02840309334873314,
      "head_error_mean": 0.5555555555555556,
      "head_error_std": 2.290614236454256,
      "body_accuracy_mean": 0.9814814814814814,
      "body_accuracy_std": 0.07635380788180854,
      "food_correct_mean": 0.3333333333333333,
      "food_correct_std": 0.4714045207910317,
      "head_found_mean": 0.9444444444444444,
      "head_found_std": 0.2290614236454256,
      "food_found_mean": 0.6666666666666666,
      "food_found_std": 0.4714045207910317
    },
    {
      "step": 42,
      "n_episodes": 18,
      "mse_mean": 0.0035773494031066853,
      "mse_std": 0.0028041560957980903,
      "ssim_mean": 0.9522570238612816,
      "ssim_std": 0.031428469778216436,
      "head_error_mean": 0.5555555555555556,
      "head_error_std": 2.290614236454256,
      "body_accuracy_mean": 0.9629629629629629,
      "body_accuracy_std": 0.10475656017578484,
      "food_correct_mean": 0.3333333333333333,
      "food_correct_std": 0.4714045207910317,
      "head_found_mean": 0.9444444444444444,
      "head_found_std": 0.2290614236454256,
      "food_found_mean": 0.7222222222222222,
      "food_found_std": 0.44790320823880836
    },
    {
      "step": 43,
      "n_episodes": 18,
      "mse_mean": 0.003488604136679088,
      "mse_std": 0.0027107024873262533,
      "ssim_mean": 0.9526416567948515,
      "ssim_std": 0.029598761111189517,
      "head_error_mean": 0.0,
      "head_error_std": 0.0,
      "body_accuracy_mean": 0.9629629629629629,
      "body_accuracy_std": 0.10475656017578484,
      "food_correct_mean": 0.3333333333333333,
      "food_correct_std": 0.4714045207910317,
      "head_found_mean": 1.0,
      "head_found_std": 0.0,
      "food_found_mean": 0.6666666666666666,
      "food_found_std": 0.4714045207910317
    },
    {
      "step": 44,
      "n_episodes": 18,
      "mse_mean": 0.0034777236431295933,
      "mse_std": 0.002648013495757506,
      "ssim_mean": 0.952222866575863,
      "ssim_std": 0.028092120269686823,
      "head_error_mean": 0.5555555555555556,
      "head_error_std": 2.290614236454256,
      "body_accuracy_mean": 0.9814814814814814,
      "body_accuracy_std": 0.07635380788180854,
      "food_correct_mean": 0.3333333333333333,
      "food_correct_std": 0.4714045207910317,
      "head_found_mean": 0.9444444444444444,
      "head_found_std": 0.2290614236454256,
      "food_found_mean": 0.6666666666666666,
      "food_found_std": 0.4714045207910317
    },
    {
      "step": 45,
      "n_episodes": 18,
      "mse_mean": 0.003497076658744744,
      "mse_std": 0.002760424883281428,
      "ssim_mean": 0.9519098651848957,
      "ssim_std": 0.03145664981821386,
      "head_error_mean": 0.5555555555555556,
      "head_error_std": 2.290614236454256,
      "body_accuracy_mean": 0.9444444444444444,
      "body_accuracy_std": 0.16666666666666669,
      "food_correct_mean": 0.3333333333333333,
      "food_correct_std": 0.4714045207910317,
      "head_found_mean": 0.9444444444444444,
      "head_found_std": 0.2290614236454256,
      "food_found_mean": 0.6666666666666666,
      "food_found_std": 0.4714045207910317
    },
    {
      "step": 46,
      "n_episodes": 18,
      "mse_mean": 0.0033248697209273814,
      "mse_std": 0.0024678823723658693,
      "ssim_mean": 0.9528505440686152,
      "ssim_std": 0.02428044157379453,
      "head_error_mean": 0.5555555555555556,
      "head_error_std": 2.290614236454256,
      "body_accuracy_mean": 0.9814814814814814,
      "body_accuracy_std": 0.07635380788180854,
      "food_correct_mean": 0.3333333333333333,
      "food_correct_std": 0.4714045207910317,
      "head_found_mean": 0.9444444444444444,
      "head_found_std": 0.2290614236454256,
      "food_found_mean": 0.6666666666666666,
      "food_found_std": 0.4714045207910317
    },
    {
      "step": 47,
      "n_episodes": 18,
      "mse_mean": 0.0033910850053315597,
      "mse_std": 0.0025941813485668647,
      "ssim_mean": 0.9537636655349063,
      "ssim_std": 0.027739188706409016,
      "head_error_mean": 0.5555555555555556,
      "head_error_std": 2.290614236454256,
      "body_accuracy_mean": 0.9629629629629629,
      "body_accuracy_std": 0.10475656017578484,
      "food_correct_mean": 0.3333333333333333,
      "food_correct_std": 0.4714045207910317,
      "head_found_mean": 0.9444444444444444,
      "head_found_std": 0.2290614236454256,
      "food_found_mean": 0.6666666666666666,
      "food_found_std": 0.4714045207910317
    },
    {
      "step": 48,
      "n_episodes": 18,
      "mse_mean": 0.0033512814963311635,
      "mse_std": 0.0024987717587541857,
      "ssim_mean": 0.9529804215168265,
      "ssim_std": 0.027717252830756153,
      "head_error_mean": 0.0,
      "head_error_std": 0.0,
      "body_accuracy_mean": 0.9814814814814814,
      "body_accuracy_std": 0.07635380788180854,
      "food_correct_mean": 0.3333333333333333,
      "food_correct_std": 0.4714045207910317,
      "head_found_mean": 1.0,
      "head_found_std": 0.0,
      "food_found_mean": 0.6666666666666666,
      "food_found_std": 0.4714045207910317
    },
    {
      "step": 49,
      "n_episodes": 18,
      "mse_mean": 0.0034050668796099773,
      "mse_std": 0.0025918831847922567,
      "ssim_mean": 0.955713563748926,
      "ssim_std": 0.02675846628812656,
      "head_error_mean": 0.0,
      "head_error_std": 0.0,
      "body_accuracy_mean": 0.9814814814814814,
      "body_accuracy_std": 0.07635380788180854,
      "food_correct_mean": 0.3333333333333333,
      "food_correct_std": 0.4714045207910317,
      "head_found_mean": 1.0,
      "head_found_std": 0.0,
      "food_found_mean": 0.6666666666666666,
      "food_found_std": 0.4714045207910317
    },
    {
      "step": 50,
      "n_episodes": 18,
      "mse_mean": 0.0034117584311085616,
      "mse_std": 0.0024767568069670796,
      "ssim_mean": 0.9540223526114288,
      "ssim_std": 0.025526597651678317,
      "head_error_mean": 0.0,
      "head_error_std": 0.0,
      "body_accuracy_mean": 0.9814814814814814,
      "body_accuracy_std": 0.07635380788180854,
      "food_correct_mean": 0.3333333333333333,
      "food_correct_std": 0.4714045207910317,
      "head_found_mean": 1.0,
      "head_found_std": 0.0,
      "food_found_mean": 0.6666666666666666,
      "food_found_std": 0.4714045207910317
    },
    {
      "step": 51,
      "n_episodes": 18,
      "mse_mean": 0.003395186479666437,
      "mse_std": 0.002446106791529025,
      "ssim_mean": 0.9515495719240532,
      "ssim_std": 0.028600620748762042,
      "head_error_mean": 0.0,
      "head_error_std": 0.0,
      "body_accuracy_mean": 0.9814814814814814,
      "body_accuracy_std": 0.07635380788180854,
      "food_correct_mean": 0.3333333333333333,
      "food_correct_std": 0.4714045207910317,
      "head_found_mean": 1.0,
      "head_found_std": 0.0,
      "food_found_mean": 0.6666666666666666,
      "food_found_std": 0.4714045207910317
    },
    {
      "step": 52,
      "n_episodes": 18,
      "mse_mean": 0.0035611531946528885,
      "mse_std": 0.0026026545584083845,
      "ssim_mean": 0.951299008277166,
      "ssim_std": 0.02961533474564999,
      "head_error_mean": 0.0,
      "head_error_std": 0.0,
      "body_accuracy_mean": 0.9814814814814814,
      "body_accuracy_std": 0.07635380788180854,
      "food_correct_mean": 0.3333333333333333,
      "food_correct_std": 0.4714045207910317,
      "head_found_mean": 1.0,
      "head_found_std": 0.0,
      "food_found_mean": 0.7222222222222222,
      "food_found_std": 0.44790320823880836
    },
    {
      "step": 53,
      "n_episodes": 18,
      "mse_mean": 0.0035569305070326765,
      "mse_std": 0.00257045640859504,
      "ssim_mean": 0.9489276624952855,
      "ssim_std": 0.029124035467461378,
      "head_error_mean": 0.0,
      "head_error_std": 0.0,
      "body_accuracy_mean": 0.9814814814814814,
      "body_accuracy_std": 0.07635380788180854,
      "food_correct_mean": 0.3333333333333333,
      "food_correct_std": 0.4714045207910317,
      "head_found_mean": 1.0,
      "head_found_std": 0.0,
      "food_found_mean": 0.6666666666666666,
      "food_found_std": 0.4714045207910317
    },
    {
      "step": 54,
      "n_episodes": 18,
      "mse_mean": 0.003742100674167482,
      "mse_std": 0.0026177493961206492,
      "ssim_mean": 0.9498172941571791,
      "ssim_std": 0.028547523926030684,
      "head_error_mean": 0.0,
      "head_error_std": 0.0,
      "body_accuracy_mean": 0.9814814814814814,
      "body_accuracy_std": 0.07635380788180854,
      "food_correct_mean": 0.3333333333333333,
      "food_correct_std": 0.4714045207910317,
      "head_found_mean": 1.0,
      "head_found_std": 0.0,
      "food_found_mean": 0.7777777777777778,
      "food_found_std": 0.41573970964154905
    },
    {
      "step": 55,
      "n_episodes": 18,
      "mse_mean": 0.0035950880641356284,
      "mse_std": 0.002612857975858053,
      "ssim_mean": 0.9528789073339031,
      "ssim_std": 0.026694032700310462,
      "head_error_mean": 0.0,
      "head_error_std": 0.0,
      "body_accuracy_mean": 0.9814814814814814,
      "body_accuracy_std": 0.07635380788180854,
      "food_correct_mean": 0.3333333333333333,
      "food_correct_std": 0.4714045207910317,
      "head_found_mean": 1.0,
      "head_found_std": 0.0,
      "food_found_mean": 0.7222222222222222,
      "food_found_std": 0.44790320823880836
    },
    {
      "step": 56,
      "n_episodes": 18,
      "mse_mean": 0.003690320279222053,
      "mse_std": 0.0026308747559907167,
      "ssim_mean": 0.9528910237800559,
      "ssim_std": 0.027336374056372126,
      "head_error_mean": 0.0,
      "head_error_std": 0.0,
      "body_accuracy_mean": 0.9814814814814814,
      "body_accuracy_std": 0.07635380788180854,
      "food_correct_mean": 0.3333333333333333,
      "food_correct_std": 0.4714045207910317,
      "head_found_mean": 1.0,
      "head_found_std": 0.0,
      "food_found_mean": 0.7222222222222222,
      "food_found_std": 0.44790320823880836
    },
    {
      "step": 57,
      "n_episodes": 18,
      "mse_mean": 0.0037425078605287532,
      "mse_std": 0.0027320408070121553,
      "ssim_mean": 0.9526918626010333,
      "ssim_std": 0.029257777027575097,
      "head_error_mean": 0.0,
      "head_error_std": 0.0,
      "body_accuracy_mean": 0.9814814814814814,
      "body_accuracy_std": 0.07635380788180854,
      "food_correct_mean": 0.3333333333333333,
      "food_correct_std": 0.4714045207910317,
      "head_found_mean": 1.0,
      "head_found_std": 0.0,
      "food_found_mean": 0.7777777777777778,
      "food_found_std": 0.41573970964154905
    },
    {
      "step": 58,
      "n_episodes": 18,
      "mse_mean": 0.0038360313836973445,
      "mse_std": 0.0028388722827416227,
      "ssim_mean": 0.950470853410596,
      "ssim_std": 0.031312309941720406,
      "head_error_mean": 0.5555555555555556,
      "head_error_std": 2.290614236454256,
      "body_accuracy_mean": 0.9629629629629629,
      "body_accuracy_std": 0.10475656017578484,
      "food_correct_mean": 0.3333333333333333,
      "food_correct_std": 0.4714045207910317,
      "head_found_mean": 0.9444444444444444,
      "head_found_std": 0.2290614236454256,
      "food_found_mean": 0.7777777777777778,
      "food_found_std": 0.41573970964154905
    },
    {
      "step": 59,
      "n_episodes": 18,
      "mse_mean": 0.003636034552452353,
      "mse_std": 0.0026301781914789793,
      "ssim_mean": 0.9504008242573752,
      "ssim_std": 0.02933405941754007,
      "head_error_mean": 0.0,
      "head_error_std": 0.0,
      "body_accuracy_mean": 0.9629629629629629,
      "body_accuracy_std": 0.10475656017578484,
      "food_correct_mean": 0.3333333333333333,
      "food_correct_std": 0.4714045207910317,
      "head_found_mean": 1.0,
      "head_found_std": 0.0,
      "food_found_mean": 0.7222222222222222,
      "food_found_std": 0.44790320823880836
    }
  ],
  "horizon": {
    "early": {
      "mse": {
        "mean": 0.0017387175635245522,
        "std": 0.001897535477549125
      },
      "ssim": {
        "mean": 0.9625770292127279,
        "std": 0.026791689118087214
      },
      "head_error": {
        "mean": 0.10880829015544041,
        "std": 1.0146977546025822
      },
      "body_accuracy": {
        "mean": 0.9749568221070812,
        "std": 0.09029033245324856
      },
      "food_correct": {
        "mean": 0.5492227979274611,
        "std": 0.4975712171781968
      },
      "head_found": {
        "mean": 0.9896373056994818,
        "std": 0.1012684988895962
      },
      "food_found": {
        "mean": 0.6580310880829016,
        "std": 0.4743692393055584
      }
    },
    "late": {
      "mse": {
        "mean": 0.0031483018856346867,
        "std": 0.0024661511632443067
      },
      "ssim": {
        "mean": 0.9534614271514541,
        "std": 0.02928803878029495
      },
      "head_error": {
        "mean": 0.14555555555555555,
        "std": 1.193469369444591
      },
      "body_accuracy": {
        "mean": 0.9796296296296297,
        "std": 0.08137619460266605
      },
      "food_correct": {
        "mean": 0.3466666666666667,
        "std": 0.47590848793532653
      },
      "head_found": {
        "mean": 0.9855555555555555,
        "std": 0.11931388213085603
      },
      "food_found": {
        "mean": 0.6422222222222222,
        "std": 0.47934626263920416
      }
    }
  },
  "num_episodes": 20,
  "total_frames": 1093,
  "per_episode": [
    {
      "episode_idx": 0,
      "num_steps": 6,
      "mse_mean": 0.0006067795281220848,
      "ssim_mean": 0.9766959416334707,
      "head_error_mean": 1.6666666666666667,
      "body_accuracy_mean": 1.0,
      "food_correct_mean": 1.0
    },
    {
      "episode_idx": 1,
      "num_steps": 7,
      "mse_mean": 0.0031094939580985476,
      "ssim_mean": 0.9669356413777904,
      "head_error_mean": 0.14285714285714285,
      "body_accuracy_mean": 0.9285714285714286,
      "food_correct_mean": 0.0
    },
    {
      "episode_idx": 2,
      "num_steps": 60,
      "mse_mean": 4.786990416505432e-06,
      "ssim_mean": 0.998530797479436,
      "head_error_mean": 0.0,
      "body_accuracy_mean": 1.0,
      "food_correct_mean": 1.0
    },
    {
      "episode_idx": 3,
      "num_steps": 60,
      "mse_mean": 0.006140438735019416,
      "ssim_mean": 0.9092506187022189,
      "head_error_mean": 0.0,
      "body_accuracy_mean": 1.0,
      "food_correct_mean": 0.0
    },
    {
      "episode_idx": 4,
      "num_steps": 60,
      "mse_mean": 0.004007821828660478,
      "ssim_mean": 0.9500210836991829,
      "head_error_mean": 0.0,
      "body_accuracy_mean": 1.0,
      "food_correct_mean": 0.05
    },
    {
      "episode_idx": 5,
      "num_steps": 60,
      "mse_mean": 0.0022397084601019895,
      "ssim_mean": 0.9640189864932183,
      "head_error_mean": 0.0,
      "body_accuracy_mean": 1.0,
      "food_correct_mean": 0.23333333333333334
    },
    {
      "episode_idx": 6,
      "num_steps": 60,
      "mse_mean": 0.005505198830360314,
      "ssim_mean": 0.9378578753314095,
      "head_error_mean": 0.3333333333333333,
      "body_accuracy_mean": 0.9722222222222221,
      "food_correct_mean": 0.05
    },
    {
      "episode_idx": 7,
      "num_steps": 60,
      "mse_mean": 0.006307225018220682,
      "ssim_mean": 0.9102420965167813,
      "head_error_mean": 1.35,
      "body_accuracy_mean": 0.9722222222222222,
      "food_correct_mean": 0.03333333333333333
    },
    {
      "episode_idx": 8,
      "num_steps": 60,
      "mse_mean": 0.00554997016059436,
      "ssim_mean": 0.9421865599445713,
      "head_error_mean": 0.0,
      "body_accuracy_mean": 1.0,
      "food_correct_mean": 0.05
    },
    {
      "episode_idx": 9,
      "num_steps": 60,
      "mse_mean": 0.0006986489288768401,
      "ssim_mean": 0.9773147251144914,
      "head_error_mean": 0.0,
      "body_accuracy_mean": 1.0,
      "food_correct_mean": 1.0
    },
    {
      "episode_idx": 10,
      "num_steps": 60,
      "mse_mean": 0.0005299617024926798,
      "ssim_mean": 0.9782922551734348,
      "head_error_mean": 0.0,
      "body_accuracy_mean": 1.0,
      "food_correct_mean": 1.0
    },
    {
      "episode_idx": 11,
      "num_steps": 60,
      "mse_mean": 0.0020165321506889692,
      "ssim_mean": 0.9682738801990909,
      "head_error_mean": 0.0,
      "body_accuracy_mean": 1.0,
      "food_correct_mean": 0.2
    },
    {
      "episode_idx": 12,
      "num_steps": 60,
      "mse_mean": 0.0004197159669881027,
      "ssim_mean": 0.9794411789515504,
      "head_error_mean": 0.0,
      "body_accuracy_mean": 1.0,
      "food_correct_mean": 1.0
    },
    {
      "episode_idx": 13,
      "num_steps": 60,
      "mse_mean": 0.0038324076410693425,
      "ssim_mean": 0.9313434432367355,
      "head_error_mean": 0.3333333333333333,
      "body_accuracy_mean": 0.9555555555555555,
      "food_correct_mean": 0.0
    },
    {
      "episode_idx": 14,
      "num_steps": 60,
      "mse_mean": 0.003205656702084525,
      "ssim_mean": 0.9472197721826177,
      "head_error_mean": 0.0,
      "body_accuracy_mean": 0.7277777777777776,
      "food_correct_mean": 0.1
    },
    {
      "episode_idx": 15,
      "num_steps": 60,
      "mse_mean": 0.003263716543248544,
      "ssim_mean": 0.9404333913610994,
      "head_error_mean": 0.16666666666666666,
      "body_accuracy_mean": 0.9944444444444444,
      "food_correct_mean": 0.0
    },
    {
      "episode_idx": 16,
      "num_steps": 60,
      "mse_mean": 0.00042809933488570097,
      "ssim_mean": 0.9804004388382472,
      "head_error_mean": 0.0,
      "body_accuracy_mean": 1.0,
      "food_correct_mean": 1.0
    },
    {
      "episode_idx": 17,
      "num_steps": 60,
      "mse_mean": 0.00364963870573168,
      "ssim_mean": 0.9527624080224902,
      "head_error_mean": 0.0,
      "body_accuracy_mean": 1.0,
      "food_correct_mean": 0.0
    },
    {
      "episode_idx": 18,
      "num_steps": 60,
      "mse_mean": 2.3834903413444408e-05,
      "ssim_mean": 0.9959974853545328,
      "head_error_mean": 0.16666666666666666,
      "body_accuracy_mean": 1.0,
      "food_correct_mean": 1.0
    },
    {
      "episode_idx": 19,
      "num_steps": 60,
      "mse_mean": 0.00457058826308033,
      "ssim_mean": 0.9241451023142215,
      "head_error_mean": 0.0,
      "body_accuracy_mean": 1.0,
      "food_correct_mean": 0.15
    }
  ]
}